certbot_dns_ispconfig/__init__.py
certbot_dns_ispconfig/dns_ispconfig.py
certbot_dns_ispconfig/dns_ispconfig_test.py
certbot_dns_ispconfig-0.3.1.dist-info/LICENSE.txt
certbot_dns_ispconfig-0.3.1.dist-info/METADATA
certbot_dns_ispconfig-0.3.1.dist-info/WHEEL
certbot_dns_ispconfig-0.3.1.dist-info/RECORD
