Metadata-Version: 2.3
Name: certbot-dns-ispconfig
Version: 0.3.1
Summary: ispconfig DNS Authenticator plugin for Certbot
License: Apache-2.0
Keywords: certbot,dns,ispconfig,authenticator,plugin
Author: Matthias Bilger
Author-email: matthias@bilger.info
Requires-Python: >=3.8
Classifier: License :: OSI Approved :: Apache Software License
Classifier: Programming Language :: Python :: 3
Classifier: Programming Language :: Python :: 3.8
Classifier: Programming Language :: Python :: 3.9
Classifier: Programming Language :: Python :: 3.10
Classifier: Programming Language :: Python :: 3.11
Classifier: Programming Language :: Python :: 3.12
Classifier: Programming Language :: Python :: 3.13
Requires-Dist: acme (>=2.11.0)
Requires-Dist: certbot (>=2.11.0)
Requires-Dist: mock
Requires-Dist: requests
Requires-Dist: requests-mock
Requires-Dist: setuptools
